chapter 3/ex10/limiter.vhdl
ENTITY limiter IS
    PORT (
        data_in, lower, upper : IN INTEGER;
        data_out : OUT INTEGER;
        out_of_bound : OUT BIT);
END ENTITY limiter;

ARCHITECTURE behav OF limiter IS
BEGIN

    limit : PROCESS (data_in, lower, upper) IS
    BEGIN
        IF data_in < lower THEN
            data_out <= lower;
            out_of_bound <= '1';
        ELSIF data_in > upper THEN
            data_out <= upper;
            out_of_bound <= '1';
        ELSE
            data_out <= data_in;
            out_of_bound <= '0';
        END IF;
    END PROCESS limit;

END ARCHITECTURE behav;

chapter 3/ex10/test_limiter.vhdl
entity test_limiter is
end entity test_limiter;

architecture test of test_limiter is
    signal data_in, lower, upper, data_out : integer := 0;
    signal out_of_limit : bit := '0';
begin
    dut : entity work.limiter(behav)
    port map (data_in, lower, upper, data_out, out_of_limit);
    stimulus : process is
    begin
        data_in <= 0; lower <= (-10); upper <= 10; wait for 10 ns;
        data_in <= (-9); wait for 10 ns;
        data_in <= (-10); wait for 10 ns;
        data_in <= (-11); wait for 10 ns;
        data_in <= integer'low; wait for 10 ns;
        data_in <= 9; wait for 10 ns;
        data_in <= 10; wait for 10 ns;
        data_in <= 11; wait for 10 ns;
        data_in <= integer'high; wait for 10 ns;
        wait;
    end process stimulus;
end architecture test;

chapter 3/ex10/test_limiter.vcd
$date
  Thu Oct 24 15:31:25 2024
$end
$version
  GHDL v0
$end
$timescale
  1 fs
$end
$scope module standard $end
$upscope $end
$scope module test_limiter $end
$var integer 32 ! data_in $end
$var integer 32 " lower $end
$var integer 32 # upper $end
$var integer 32 $ data_out $end
$var reg 1 % out_of_limit $end
$scope module dut $end
$var integer 32 & data_in $end
$var integer 32 ' lower $end
$var integer 32 ( upper $end
$var integer 32 ) data_out $end
$var reg 1 * out_of_bound $end
$upscope $end
$upscope $end
$enddefinitions $end
#0
b0 !
b11111111111111111111111111110110 "
b1010 #
b0 $
0%
b0 &
b11111111111111111111111111110110 '
b1010 (
b0 )
0*
#10000000
b11111111111111111111111111110111 !
b11111111111111111111111111110111 $
b11111111111111111111111111110111 &
b11111111111111111111111111110111 )
#20000000
b11111111111111111111111111110110 !
b11111111111111111111111111110110 $
b11111111111111111111111111110110 &
b11111111111111111111111111110110 )
#30000000
b11111111111111111111111111110101 !
1%
b11111111111111111111111111110101 &
1*
#40000000
b10000000000000000000000000000000 !
b10000000000000000000000000000000 &
#50000000
b1001 !
b1001 $
0%
b1001 &
b1001 )
0*
#60000000
b1010 !
b1010 $
b1010 &
b1010 )
#70000000
b1011 !
1%
b1011 &
1*
#80000000
b1111111111111111111111111111111 !
b1111111111111111111111111111111 &
