chapter 2/ex11/integrator.vhdl
ENTITY integrator IS
    PORT (
        data : IN REAL;
        clk : IN BIT;
        integral : OUT REAL);
END ENTITY integrator;

ARCHITECTURE behav OF integrator IS
BEGIN
    integrate : PROCESS IS
        VARIABLE sum : REAL := 0.0;
    BEGIN
        IF RISING_EDGE(clk) THEN
            sum := sum + data;
        END IF;
        integral <= sum;
        WAIT ON clk;
    END PROCESS integrate;
END ARCHITECTURE;

chapter 2/ex11/test_integrator.vhdl
ENTITY test_integrator IS
END ENTITY test_integrator;

architecture test of test_integrator is
    signal data, integral : real := 0.0;
    signal clk : bit;
begin

    dut : entity work.integrator(behav)
    port map (data, clk, integral);
    
    clock : process is
    begin
        clk <= '1'; wait for 5 ns;
        clk <= '0'; wait for 5 ns;
    end process clock;
    
    stimulus : process is
    begin
        data <= 0.01; wait for 20 ns;
        data <= 0.1; wait for 20 ns;
        data <= (-0.09); wait for 20 ns;
    end process stimulus;

end architecture;

chapter 2/ex11/test_integrator.vcd
$date
  Wed Oct 23 15:30:18 2024
$end
$version
  GHDL v0
$end
$timescale
  1 fs
$end
$scope module standard $end
$upscope $end
$scope module test_integrator $end
$var real 64 ! data $end
$var real 64 " integral $end
$var reg 1 # clk $end
$scope module dut $end
$var real 64 $ data $end
$var reg 1 % clk $end
$var real 64 & integral $end
$upscope $end
$upscope $end
$enddefinitions $end
#0
r1.0e-2 !
r1.0e-2 "
1#
r1.0e-2 $
1%
r1.0e-2 &
#5000000
0#
0%
#10000000
r2.0e-2 "
1#
1%
r2.0e-2 &
#15000000
0#
0%
#20000000
r1.0e-1 !
r1.2000000000000001e-1 "
1#
r1.0e-1 $
1%
r1.2000000000000001e-1 &
#25000000
0#
0%
#30000000
r2.2000000000000003e-1 "
1#
1%
r2.2000000000000003e-1 &
#35000000
0#
0%
#40000000
r-9.0e-2 !
r1.3000000000000003e-1 "
1#
r-9.0e-2 $
1%
r1.3000000000000003e-1 &
#45000000
0#
0%
#50000000
r4.0000000000000036e-2 "
1#
1%
r4.0000000000000036e-2 &
#55000000
0#
0%
#60000000
r1.0e-2 !
r5.000000000000004e-2 "
1#
r1.0e-2 $
1%
r5.000000000000004e-2 &
#65000000
0#
0%
#70000000
r6.000000000000004e-2 "
1#
1%
r6.000000000000004e-2 &
#75000000
0#
0%
#80000000
r1.0e-1 !
r1.6000000000000003e-1 "
1#
r1.0e-1 $
1%
r1.6000000000000003e-1 &
#85000000
0#
0%
#90000000
r2.6e-1 "
1#
1%
r2.6e-1 &
#95000000
0#
0%
#100000000
r-9.0e-2 !
r1.7e-1 "
1#
r-9.0e-2 $
1%
r1.7e-1 &
#105000000
0#
0%
#110000000
r8.000000000000002e-2 "
1#
1%
r8.000000000000002e-2 &
#115000000
0#
0%
#120000000
r1.0e-2 !
r9.000000000000001e-2 "
1#
r1.0e-2 $
1%
r9.000000000000001e-2 &
#125000000
0#
0%
#130000000
r1.0e-1 "
1#
1%
r1.0e-1 &
#135000000
0#
0%
#140000000
r1.0e-1 !
r2.0e-1 "
1#
r1.0e-1 $
1%
r2.0e-1 &
#145000000
0#
0%
#150000000
r3.0000000000000004e-1 "
1#
1%
r3.0000000000000004e-1 &
#155000000
0#
0%
#160000000
r-9.0e-2 !
r2.1000000000000005e-1 "
1#
r-9.0e-2 $
1%
r2.1000000000000005e-1 &
#165000000
0#
0%
#170000000
r1.2000000000000005e-1 "
1#
1%
r1.2000000000000005e-1 &
#175000000
0#
0%
#180000000
r1.0e-2 !
r1.3000000000000006e-1 "
1#
r1.0e-2 $
1%
r1.3000000000000006e-1 &
#185000000
0#
0%
#190000000
r1.4000000000000007e-1 "
1#
1%
r1.4000000000000007e-1 &
#195000000
0#
0%
#200000000
r1.0e-1 !
r2.4000000000000007e-1 "
1#
r1.0e-1 $
1%
r2.4000000000000007e-1 &
