chapter 4/ex6/trace.vhdl
ENTITY trace IS
    PORT (
        v : IN bit_vector;
        sum : OUT NATURAL
    );
END ENTITY trace;

ARCHITECTURE behav OF trace IS

BEGIN

    summing : PROCESS (v) IS
        VARIABLE accum : NATURAL;
    BEGIN
        accum := 0;
        FOR i IN v'RANGE LOOP
            accum := accum + 1 WHEN v(i);
        END LOOP;
        sum <= accum;
    END PROCESS summing;

END ARCHITECTURE;

chapter 4/ex6/test_trace.vhdl
ENTITY test_trace IS
END ENTITY test_trace;

ARCHITECTURE test OF test_trace IS
    SIGNAL source : bit_vector(1 TO 10);
    SIGNAL sum : NATURAL;
BEGIN

    dut : ENTITY work.trace(behav)
        PORT MAP(source, sum);

    stimulus : PROCESS IS
    BEGIN
        source <= (OTHERS => '1');
        WAIT FOR 5 ns;
        source <= ('1', OTHERS => '0');
        WAIT FOR 5 ns;
        source <= ('1', '1', '1', OTHERS => '0');
        WAIT FOR 5 ns;
    END PROCESS stimulus;

END ARCHITECTURE;

chapter 4/ex6/test_trace.vcd
$date
  Fri Oct 25 21:42:55 2024
$end
$version
  GHDL v0
$end
$timescale
  1 fs
$end
$scope module standard $end
$upscope $end
$scope module test_trace $end
$var reg 10 ! source[1:10] $end
$var integer 32 " sum $end
$scope module dut $end
$var reg 10 # v[1:10] $end
$var integer 32 $ sum $end
$upscope $end
$upscope $end
$enddefinitions $end
#0
b1111111111 !
b1010 "
b1111111111 #
b1010 $
#5000000
b1000000000 !
b1 "
b1000000000 #
b1 $
#10000000
b1110000000 !
b11 "
b1110000000 #
b11 $
#15000000
b1111111111 !
b1010 "
b1111111111 #
b1010 $
#20000000
b1000000000 !
b1 "
b1000000000 #
b1 $
#25000000
b1110000000 !
b11 "
b1110000000 #
b11 $
#30000000
b1111111111 !
b1010 "
b1111111111 #
b1010 $
#35000000
b1000000000 !
b1 "
b1000000000 #
b1 $
#40000000
b1110000000 !
b11 "
b1110000000 #
b11 $
#45000000
b1111111111 !
b1010 "
b1111111111 #
b1010 $
#50000000
b1000000000 !
b1 "
b1000000000 #
b1 $
#55000000
b1110000000 !
b11 "
b1110000000 #
b11 $
#60000000
b1111111111 !
b1010 "
b1111111111 #
b1010 $
#65000000
b1000000000 !
b1 "
b1000000000 #
b1 $
#70000000
b1110000000 !
b11 "
b1110000000 #
b11 $
#75000000
b1111111111 !
b1010 "
b1111111111 #
b1010 $
#80000000
b1000000000 !
b1 "
b1000000000 #
b1 $
#85000000
b1110000000 !
b11 "
b1110000000 #
b11 $
#90000000
b1111111111 !
b1010 "
b1111111111 #
b1010 $
#95000000
b1000000000 !
b1 "
b1000000000 #
b1 $
#100000000
b1110000000 !
b11 "
b1110000000 #
b11 $
