chapter 4/ex9/register_file.vhdl
PACKAGE dtypes IS
    SUBTYPE word IS bit_vector(0 TO 31);
    CONSTANT default_word : word := (others => '0');
    SUBTYPE address IS INTEGER RANGE 0 TO 15;
    TYPE the_file IS ARRAY (address) OF word;
END PACKAGE dtypes;

USE work.dtypes.ALL;

ENTITY register_file IS
    PORT (
        din : IN word;
        w_adr : IN address;
        r_adr : IN address;
        w_en : IN BIT;
        dout : OUT word
    );
END ENTITY register_file;

ARCHITECTURE behav OF register_file IS
BEGIN

    read_write : PROCESS (ALL) IS
        VARIABLE state : the_file := (OTHERS => default_word);
    BEGIN

        IF w_en THEN
            state(w_adr) := din;
        END IF;

        dout <= state(r_adr);

    END PROCESS read_write;

END ARCHITECTURE;

chapter 4/ex9/test_register.vhdl
ENTITY test_register IS
END ENTITY test_register;

USE work.dtypes.ALL;

ARCHITECTURE test OF test_register IS
    SIGNAL din, dout : word;
    SIGNAL w_adr, r_adr : address;
    SIGNAL w_en : BIT;
BEGIN

    dut : ENTITY work.register_file(behav)
        PORT MAP(din, w_adr, r_adr, w_en, dout);

    stimulus : PROCESS IS
    BEGIN

        din <= ('1', '1', others => '0');
        w_adr <= 6;
        r_adr <= 1;
        w_en <= '1';
        WAIT FOR 5 ns;

        din <= ('0', '1', '1', others => '0');
        w_adr <= 1;
        r_adr <= 6;
        WAIT FOR 5 ns;

        din <= (others => '1');
        w_en <= '0';
        r_adr <= 1;
        WAIT FOR 5 ns;

        w_adr <= 15;
        r_adr <= 15;
        WAIT FOR 5 ns;
        
        w_en <= '1';
        wait for 5 ns;
        
        r_adr <= 2;
        wait for 5 ns;

    END PROCESS stimulus;

END ARCHITECTURE;

chapter 4/ex9/test_register.vcd
$date
  Mon Oct 28 15:40:11 2024
$end
$version
  GHDL v0
$end
$timescale
  1 fs
$end
$scope module standard $end
$upscope $end
$scope module dtypes $end
$upscope $end
$scope module test_register $end
$var reg 32 ! din[0:31] $end
$var reg 32 " dout[0:31] $end
$var integer 32 # w_adr $end
$var integer 32 $ r_adr $end
$var reg 1 % w_en $end
$scope module dut $end
$var reg 32 & din[0:31] $end
$var integer 32 ' w_adr $end
$var integer 32 ( r_adr $end
$var reg 1 ) w_en $end
$var reg 32 * dout[0:31] $end
$upscope $end
$upscope $end
$enddefinitions $end
#0
b11000000000000000000000000000000 !
b00000000000000000000000000000000 "
b110 #
b1 $
1%
b11000000000000000000000000000000 &
b110 '
b1 (
1)
b00000000000000000000000000000000 *
#5000000
b01100000000000000000000000000000 !
b11000000000000000000000000000000 "
b1 #
b110 $
b01100000000000000000000000000000 &
b1 '
b110 (
b11000000000000000000000000000000 *
#10000000
b11111111111111111111111111111111 !
b01100000000000000000000000000000 "
b1 $
0%
b11111111111111111111111111111111 &
b1 (
0)
b01100000000000000000000000000000 *
#15000000
b00000000000000000000000000000000 "
b1111 #
b1111 $
b1111 '
b1111 (
b00000000000000000000000000000000 *
#20000000
b11111111111111111111111111111111 "
1%
1)
b11111111111111111111111111111111 *
#25000000
b00000000000000000000000000000000 "
b10 $
b10 (
b00000000000000000000000000000000 *
#30000000
b11000000000000000000000000000000 !
b01100000000000000000000000000000 "
b110 #
b1 $
b11000000000000000000000000000000 &
b110 '
b1 (
b01100000000000000000000000000000 *
#35000000
b01100000000000000000000000000000 !
b11000000000000000000000000000000 "
b1 #
b110 $
b01100000000000000000000000000000 &
b1 '
b110 (
b11000000000000000000000000000000 *
#40000000
b11111111111111111111111111111111 !
b01100000000000000000000000000000 "
b1 $
0%
b11111111111111111111111111111111 &
b1 (
0)
b01100000000000000000000000000000 *
#45000000
b11111111111111111111111111111111 "
b1111 #
b1111 $
b1111 '
b1111 (
b11111111111111111111111111111111 *
#50000000
1%
1)
#55000000
b00000000000000000000000000000000 "
b10 $
b10 (
b00000000000000000000000000000000 *
#60000000
b11000000000000000000000000000000 !
b01100000000000000000000000000000 "
b110 #
b1 $
b11000000000000000000000000000000 &
b110 '
b1 (
b01100000000000000000000000000000 *
#65000000
b01100000000000000000000000000000 !
b11000000000000000000000000000000 "
b1 #
b110 $
b01100000000000000000000000000000 &
b1 '
b110 (
b11000000000000000000000000000000 *
#70000000
b11111111111111111111111111111111 !
b01100000000000000000000000000000 "
b1 $
0%
b11111111111111111111111111111111 &
b1 (
0)
b01100000000000000000000000000000 *
#75000000
b11111111111111111111111111111111 "
b1111 #
b1111 $
b1111 '
b1111 (
b11111111111111111111111111111111 *
#80000000
1%
1)
#85000000
b00000000000000000000000000000000 "
b10 $
b10 (
b00000000000000000000000000000000 *
#90000000
b11000000000000000000000000000000 !
b01100000000000000000000000000000 "
b110 #
b1 $
b11000000000000000000000000000000 &
b110 '
b1 (
b01100000000000000000000000000000 *
#95000000
b01100000000000000000000000000000 !
b11000000000000000000000000000000 "
b1 #
b110 $
b01100000000000000000000000000000 &
b1 '
b110 (
b11000000000000000000000000000000 *
#100000000
b11111111111111111111111111111111 !
b01100000000000000000000000000000 "
b1 $
0%
b11111111111111111111111111111111 &
b1 (
0)
b01100000000000000000000000000000 *
