chapter 4/ex12/and_or_invert.vhdl
LIBRARY ieee;
USE ieee.std_logic_1164.ALL;

ENTITY and_or_invert IS
    PORT (
        a, b : IN STD_LOGIC_VECTOR;
        y : OUT STD_LOGIC
    );
END ENTITY and_or_invert;

ARCHITECTURE behav OF and_or_invert IS

BEGIN

    aoi : PROCESS (a, b) IS
    BEGIN

        y <= NOT ( OR (a AND b));

    END PROCESS aoi;

END ARCHITECTURE;

chapter 4/ex12/test_and_or_invert.vhdl
ENTITY test_and_or_invert IS
END ENTITY;

LIBRARY ieee;
USE ieee.std_logic_1164.ALL;

ARCHITECTURE test OF test_and_or_invert IS
    SIGNAL a, b : STD_LOGIC_VECTOR(0 TO 3);
    SIGNAL y : STD_LOGIC;
BEGIN

    dut : ENTITY work.and_or_invert(behav)
        PORT MAP(a, b, y);

    stimulus : PROCESS IS
    BEGIN

        a <= ('1', '1', '0', '0');
        b <= ('0', '0', '1', '1');
        WAIT FOR 5 ns;

        b <= ('1', OTHERS => '0');
        WAIT FOR 5 ns;

        a <= (OTHERS => '1');
        WAIT FOR 5 ns;

        b <= (OTHERS => '1');
        WAIT FOR 5 ns;

        a <= (OTHERS => '0');
        WAIT FOR 5 ns;

    END PROCESS stimulus;

END ARCHITECTURE;

chapter 4/ex12/test_and_or_invert.vcd
$date
  Mon Oct 28 19:17:05 2024
$end
$version
  GHDL v0
$end
$timescale
  1 fs
$end
$scope module standard $end
$upscope $end
$scope module textio $end
$upscope $end
$scope module std_logic_1164 $end
$upscope $end
$scope module test_and_or_invert $end
$var reg 4 ! a[0:3] $end
$var reg 4 " b[0:3] $end
$var reg 1 # y $end
$scope module dut $end
$comment a is not handled $end
$comment b is not handled $end
$var reg 1 $ y $end
$upscope $end
$upscope $end
$enddefinitions $end
#0
b1100 !
b0011 "
1#
1$
#5000000
b1000 "
0#
0$
#10000000
b1111 !
#15000000
b1111 "
#20000000
b0000 !
1#
1$
#25000000
b1100 !
b0011 "
#30000000
b1000 "
0#
0$
#35000000
b1111 !
#40000000
b1111 "
#45000000
b0000 !
1#
1$
#50000000
b1100 !
b0011 "
