chapter 2/ex13/tristate.vhdl
LIBRARY ieee;
USE ieee.std_logic_1164.ALL;

ENTITY tristate_buffer IS
    PORT (
        en, din : IN STD_ULOGIC;
        dout : OUT STD_ULOGIC := 'X');
END ENTITY tristate_buffer;

ARCHITECTURE behav OF tristate_buffer IS

BEGIN

    fix : PROCESS IS
        VARIABLE state : STD_ULOGIC := 'X';
    BEGIN
        IF en ?= '0' THEN
            state := 'Z';
        ELSIF en ?= '1' THEN

            IF din ?= '0' THEN
                state := '0';
            ELSIF din ?= '1' THEN
                state := '1';
            ELSE
                state := 'X';
            END IF;

        ELSE
            state := 'X';
        END IF;
        dout <= state;
        WAIT FOR 1 ns;
    END PROCESS fix;

END ARCHITECTURE;

chapter 2/ex13/test_tristate.vhdl
entity test_tristate is
end entity test_tristate;

library ieee;
use ieee.std_logic_1164.all;

architecture test of test_tristate is
    signal en, din, dout : STD_ULOGIC;
begin
    
    dut : entity work.tristate_buffer(behav)
    port map (en, din, dout);
    
    stimulus : process is
    begin
        wait for 5 ns;
        en <= '0'; wait for 5 ns;
        en <= 'L'; wait for 5 ns;
        en <= '1'; din <= '0'; wait for 5 ns;
        din <= 'L'; wait for 5 ns;
        din <= '1'; wait for 5 ns;
        din <= 'H'; wait for 5 ns;
        din <= 'W'; wait for 5 ns;
        din <= 'X'; wait for 5 ns;
        en <= 'X';
        wait;
    end process stimulus;
    
end architecture test;

chapter 2/ex13/test_tristate.vcd
$date
  Wed Oct 23 15:37:05 2024
$end
$version
  GHDL v0
$end
$timescale
  1 fs
$end
$scope module standard $end
$upscope $end
$scope module textio $end
$upscope $end
$scope module std_logic_1164 $end
$upscope $end
$scope module test_tristate $end
$var reg 1 ! en $end
$var reg 1 " din $end
$var reg 1 # dout $end
$scope module dut $end
$var reg 1 $ en $end
$var reg 1 % din $end
$var reg 1 & dout $end
$upscope $end
$upscope $end
$enddefinitions $end
#0
U!
U"
X#
U$
U%
X&
#1000000
#2000000
#3000000
#4000000
#5000000
0!
0$
#6000000
Z#
Z&
#7000000
#8000000
#9000000
#10000000
L!
L$
#11000000
#12000000
#13000000
#14000000
#15000000
1!
0"
1$
0%
#16000000
0#
0&
#17000000
#18000000
#19000000
#20000000
L"
L%
#21000000
#22000000
#23000000
#24000000
#25000000
1"
1%
#26000000
1#
1&
#27000000
#28000000
#29000000
#30000000
H"
H%
#31000000
#32000000
#33000000
#34000000
#35000000
W"
W%
#36000000
X#
X&
#37000000
#38000000
#39000000
#40000000
X"
X%
#41000000
#42000000
#43000000
#44000000
#45000000
X!
X$
