chapter 4/ex13/decode3to8.vhdl
LIBRARY ieee;
USE ieee.std_logic_1164.ALL;
USE ieee.numeric_std.ALL;

ENTITY decoder IS
    PORT (
        code : IN STD_LOGIC_VECTOR(2 DOWNTO 0);
        selection : OUT STD_LOGIC_VECTOR(7 DOWNTO 0)
    );
END ENTITY;

ARCHITECTURE behav OF decoder IS
BEGIN

    decode : PROCESS (code) IS
        VARIABLE index : INTEGER RANGE 7 DOWNTO 0;
    BEGIN

        selection <= (OTHERS => '0');

        index := to_integer(unsigned(code));

        selection(index) <= '1';

    END PROCESS decode;

END ARCHITECTURE;

chapter 4/ex13/test_decode3to8.vhdl
LIBRARY ieee;
USE ieee.std_logic_1164.ALL;
USE ieee.numeric_std.ALL;

PACKAGE tests IS

    TYPE three_to_eight IS RECORD
        sample_input : STD_LOGIC_VECTOR(2 DOWNTO 0);
        delay : TIME;
        expected_output : STD_LOGIC_VECTOR(7 DOWNTO 0);
    END RECORD three_to_eight;

    TYPE sample IS ARRAY (NATURAL RANGE <>) OF three_to_eight;

    CONSTANT expected : sample := (
        (sample_input => B"000", delay => 5 ns, expected_output => B"0000_0001"),
        (sample_input => B"001", delay => 5 ns, expected_output => B"0000_0010"),
        (sample_input => B"010", delay => 5 ns, expected_output => B"0000_0100"),
        (sample_input => B"011", delay => 5 ns, expected_output => B"0000_1000"),
        (sample_input => B"100", delay => 5 ns, expected_output => B"0001_0000"),
        (sample_input => B"101", delay => 5 ns, expected_output => B"0010_0000"),
        (sample_input => B"110", delay => 5 ns, expected_output => B"0100_0000"),
        (sample_input => B"111", delay => 5 ns, expected_output => B"1000_0000")
    );

END PACKAGE tests;

ENTITY test_decode3to8 IS
END ENTITY;

LIBRARY ieee;
USE ieee.std_logic_1164.ALL;
USE ieee.numeric_std.ALL;
USE work.tests.ALL;

ARCHITECTURE test OF test_decode3to8 IS
    SIGNAL code : STD_LOGIC_VECTOR(2 DOWNTO 0);
    SIGNAL selection : STD_LOGIC_VECTOR(7 DOWNTO 0);
BEGIN

    dut : ENTITY work.decoder(behav)
        PORT MAP(code, selection);

    stimulus : PROCESS IS
    BEGIN

        FOR i IN expected'RANGE LOOP
            code <= expected(i).sample_input;
            WAIT FOR expected(i).delay;
            ASSERT selection = expected(i).expected_output REPORT "UNEXPECTED OUTPUT" SEVERITY FAILURE;
        END LOOP;

    END PROCESS stimulus;

END ARCHITECTURE;

chapter 4/ex13/test_decode3to8.vcd
$date
  Tue Oct 29 10:42:19 2024
$end
$version
  GHDL v0
$end
$timescale
  1 fs
$end
$scope module standard $end
$upscope $end
$scope module textio $end
$upscope $end
$scope module std_logic_1164 $end
$upscope $end
$scope module numeric_std $end
$upscope $end
$scope module tests $end
$upscope $end
$scope module test_decode3to8 $end
$var reg 3 ! code[2:0] $end
$var reg 8 " selection[7:0] $end
$scope module dut $end
$var reg 3 # code[2:0] $end
$var reg 8 $ selection[7:0] $end
$upscope $end
$upscope $end
$enddefinitions $end
#0
b000 !
b00000001 "
b000 #
b00000001 $
#5000000
b001 !
b00000010 "
b001 #
b00000010 $
#10000000
b010 !
b00000100 "
b010 #
b00000100 $
#15000000
b011 !
b00001000 "
b011 #
b00001000 $
#20000000
b100 !
b00010000 "
b100 #
b00010000 $
#25000000
b101 !
b00100000 "
b101 #
b00100000 $
#30000000
b110 !
b01000000 "
b110 #
b01000000 $
#35000000
b111 !
b10000000 "
b111 #
b10000000 $
#40000000
b000 !
b00000001 "
b000 #
b00000001 $
#45000000
b001 !
b00000010 "
b001 #
b00000010 $
#50000000
b010 !
b00000100 "
b010 #
b00000100 $
#55000000
b011 !
b00001000 "
b011 #
b00001000 $
#60000000
b100 !
b00010000 "
b100 #
b00010000 $
#65000000
b101 !
b00100000 "
b101 #
b00100000 $
#70000000
b110 !
b01000000 "
b110 #
b01000000 $
#75000000
b111 !
b10000000 "
b111 #
b10000000 $
#80000000
b000 !
b00000001 "
b000 #
b00000001 $
#85000000
b001 !
b00000010 "
b001 #
b00000010 $
#90000000
b010 !
b00000100 "
b010 #
b00000100 $
#95000000
b011 !
b00001000 "
b011 #
b00001000 $
#100000000
b100 !
b00010000 "
b100 #
b00010000 $
