chapter 2/ex10/ALU.vhdl
LIBRARY ieee;
USE ieee.std_logic_1164.ALL;
USE ieee.numeric_std.ALL;

ENTITY ALU IS
    PORT (
        a, b : IN SIGNED(7 DOWNTO 0);
        op : IN BIT;
        z : OUT SIGNED(8 DOWNTO 0)
    );
END ENTITY ALU;

ARCHITECTURE behav OF ALU IS
BEGIN
    operate : PROCESS IS
        VARIABLE result : SIGNED(8 DOWNTO 0);
        VARIABLE rs_a, rs_b : SIGNED(8 DOWNTO 0);
    BEGIN
        rs_a := RESIZE(a, 9);
        rs_b := RESIZE(b, 9);
        IF op THEN
            result := rs_a - rs_b;
        ELSE
            result := rs_a + rs_b;
        END IF;
        z <= result;
        WAIT FOR 1 ns;
    END PROCESS operate;
END ARCHITECTURE;

chapter 2/ex10/test_ALU.vhdl
LIBRARY ieee;
USE ieee.std_logic_1164.ALL;
USE ieee.numeric_std.ALL;

ENTITY test_ALU IS
END ENTITY test_ALU;

ARCHITECTURE test OF test_ALU IS
    SIGNAL a, b : SIGNED(7 DOWNTO 0);
    SIGNAL op : BIT;
    SIGNAL z : SIGNED(8 DOWNTO 0);
BEGIN

    dut : ENTITY work.ALU(behav)
        PORT MAP(a, b, op, z);

    stimulus : PROCESS IS
    BEGIN
        a <= X"FF";
        b <= X"01";
        op <= '0';
        WAIT FOR 5 ns;
        op <= '1';
        WAIT FOR 5 ns;
        a <= X"7F";
        b <= X"90";
        WAIT FOR 5 ns;
        op <= '0';
        WAIT FOR 5 ns;
        a <= X"80";
        b <= X"80";
        WAIT FOR 5 ns;
        op <= '1';
        WAIT FOR 5 ns;
    END PROCESS stimulus;

END ARCHITECTURE test;

chapter 2/ex10/test_ALU.vcd
$date
  Wed Oct 23 14:56:41 2024
$end
$version
  GHDL v0
$end
$timescale
  1 fs
$end
$scope module standard $end
$upscope $end
$scope module textio $end
$upscope $end
$scope module std_logic_1164 $end
$upscope $end
$scope module numeric_std $end
$upscope $end
$scope module test_alu $end
$var reg 8 ! a[7:0] $end
$var reg 8 " b[7:0] $end
$var reg 1 # op $end
$var reg 9 $ z[8:0] $end
$scope module dut $end
$var reg 8 % a[7:0] $end
$var reg 8 & b[7:0] $end
$var reg 1 ' op $end
$var reg 9 ( z[8:0] $end
$upscope $end
$upscope $end
$enddefinitions $end
#0
b11111111 !
b00000001 "
0#
bXXXXXXXXX $
b11111111 %
b00000001 &
0'
bXXXXXXXXX (
#1000000
b000000000 $
b000000000 (
#2000000
#3000000
#4000000
#5000000
1#
1'
#6000000
b111111110 $
b111111110 (
#7000000
#8000000
#9000000
#10000000
b01111111 !
b10010000 "
b01111111 %
b10010000 &
#11000000
b011101111 $
b011101111 (
#12000000
#13000000
#14000000
#15000000
0#
0'
#16000000
b000001111 $
b000001111 (
#17000000
#18000000
#19000000
#20000000
b10000000 !
b10000000 "
b10000000 %
b10000000 &
#21000000
b100000000 $
b100000000 (
#22000000
#23000000
#24000000
#25000000
1#
1'
#26000000
b000000000 $
b000000000 (
#27000000
#28000000
#29000000
#30000000
b11111111 !
b00000001 "
0#
b11111111 %
b00000001 &
0'
#31000000
#32000000
#33000000
#34000000
#35000000
1#
1'
#36000000
b111111110 $
b111111110 (
#37000000
#38000000
#39000000
#40000000
b01111111 !
b10010000 "
b01111111 %
b10010000 &
#41000000
b011101111 $
b011101111 (
#42000000
#43000000
#44000000
#45000000
0#
0'
#46000000
b000001111 $
b000001111 (
#47000000
#48000000
#49000000
#50000000
b10000000 !
b10000000 "
b10000000 %
b10000000 &
#51000000
b100000000 $
b100000000 (
#52000000
#53000000
#54000000
#55000000
1#
1'
#56000000
b000000000 $
b000000000 (
#57000000
#58000000
#59000000
#60000000
b11111111 !
b00000001 "
0#
b11111111 %
b00000001 &
0'
#61000000
#62000000
#63000000
#64000000
#65000000
1#
1'
#66000000
b111111110 $
b111111110 (
#67000000
#68000000
#69000000
#70000000
b01111111 !
b10010000 "
b01111111 %
b10010000 &
#71000000
b011101111 $
b011101111 (
#72000000
#73000000
#74000000
#75000000
0#
0'
#76000000
b000001111 $
b000001111 (
#77000000
#78000000
#79000000
#80000000
b10000000 !
b10000000 "
b10000000 %
b10000000 &
#81000000
b100000000 $
b100000000 (
#82000000
#83000000
#84000000
#85000000
1#
1'
#86000000
b000000000 $
b000000000 (
#87000000
#88000000
#89000000
#90000000
b11111111 !
b00000001 "
0#
b11111111 %
b00000001 &
0'
#91000000
#92000000
#93000000
#94000000
#95000000
1#
1'
#96000000
b111111110 $
b111111110 (
#97000000
#98000000
#99000000
#100000000
b01111111 !
b10010000 "
b01111111 %
b10010000 &
