chapter 4/ex3/diskette.vhdl
PACKAGE diskette IS
    CONSTANT sector_length : POSITIVE := 18;
    CONSTANT track_length : POSITIVE := 80;
    CONSTANT side_number : POSITIVE := 2;

    TYPE index IS RECORD
        sector : NATURAL RANGE 0 TO sector_length;
        track : NATURAL RANGE 0 TO track_length;
        sides : NATURAL RANGE 0 TO side_number;
    END RECORD index;

    TYPE occupied IS ARRAY (
    1 TO sector_length,
    1 TO track_length,
    1 TO side_number
    ) OF BIT;

END PACKAGE diskette;

USE work.diskette.ALL;
ENTITY sector_tracker IS
    PORT (
        state : IN occupied;
        ix : OUT index
    );
END ENTITY sector_tracker;

ARCHITECTURE behav OF sector_tracker IS
BEGIN

    search : PROCESS (state) IS
        -- for the first free sector and assign its location to ix
        VARIABLE temp : index;
    BEGIN
        temp := (0, 0, 0);
        outer : FOR si IN state'RANGE(1) LOOP
            FOR tr IN state'RANGE(2) LOOP
                FOR sect IN state'RANGE(3) LOOP
                    IF state(si, tr, sect) THEN
                        temp := (si, tr, sect);
                        EXIT outer;
                    END IF;
                END LOOP;
            END LOOP;
        END LOOP;
        ix <= temp;

    END PROCESS search;

END ARCHITECTURE behav;

chapter 4/ex3/test_diskette.vhdl
ENTITY test_diskette IS
END ENTITY test_diskette;

USE work.diskette.ALL;

ARCHITECTURE test OF test_diskette IS
    SIGNAL state : occupied := (OTHERS => (OTHERS => (OTHERS => '0')));
    SIGNAL ix : index := (OTHERS => 0);
    SIGNAL sector, track, sides : NATURAL;
BEGIN

    dut : ENTITY work.sector_tracker(behav)
        PORT MAP(state, ix);

    stimulus : PROCESS IS
    BEGIN
        state <= (OTHERS => (OTHERS => (OTHERS => '0')));
        WAIT FOR 1 ns;
        sector <= ix.sector;
        track <= ix.track;
        sides <= ix.sides;
        WAIT FOR 4 ns;

        state <= (
                 9 => (
                 40 => (
                 1 => '1',
                 OTHERS => '0'
                 ),
                 OTHERS => (OTHERS => '0')
                 ),
                 OTHERS => (OTHERS => (OTHERS => '0')));
        WAIT FOR 1 ns;
        sector <= ix.sector;
        track <= ix.track;
        sides <= ix.sides;
        WAIT FOR 4 ns;

        state <= (
                 1 TO 10 => (
                 3 TO 40 => (
                 1 => '1',
                 OTHERS => '0'),
                 OTHERS => (OTHERS => '0')
                 ),
                 OTHERS => (OTHERS => (OTHERS => '0')));
        WAIT FOR 1 ns;
        sector <= ix.sector;
        track <= ix.track;
        sides <= ix.sides;
        WAIT FOR 4 ns;

    END PROCESS stimulus;

END ARCHITECTURE;

chapter 4/ex3/test_diskette.vcd
$date
  Fri Oct 25 12:06:11 2024
$end
$version
  GHDL v0
$end
$timescale
  1 fs
$end
$scope module standard $end
$upscope $end
$scope module diskette $end
$upscope $end
$scope module test_diskette $end
$comment state is not handled $end
$comment ix is not handled $end
$var integer 32 ! sector $end
$var integer 32 " track $end
$var integer 32 # sides $end
$scope module dut $end
$comment state is not handled $end
$comment ix is not handled $end
$upscope $end
$upscope $end
$enddefinitions $end
#0
b0 !
b0 "
b0 #
#1000000
#5000000
#6000000
b1001 !
b101000 "
b1 #
#10000000
#11000000
b1 !
b11 "
#15000000
#16000000
b0 !
b0 "
b0 #
#20000000
#21000000
b1001 !
b101000 "
b1 #
#25000000
#26000000
b1 !
b11 "
#30000000
#31000000
b0 !
b0 "
b0 #
#35000000
#36000000
b1001 !
b101000 "
b1 #
#40000000
#41000000
b1 !
b11 "
#45000000
#46000000
b0 !
b0 "
b0 #
#50000000
#51000000
b1001 !
b101000 "
b1 #
#55000000
#56000000
b1 !
b11 "
#60000000
#61000000
b0 !
b0 "
b0 #
#65000000
#66000000
b1001 !
b101000 "
b1 #
#70000000
#71000000
b1 !
b11 "
#75000000
#76000000
b0 !
b0 "
b0 #
#80000000
#81000000
b1001 !
b101000 "
b1 #
#85000000
#86000000
b1 !
b11 "
#90000000
#91000000
b0 !
b0 "
b0 #
#95000000
#96000000
b1001 !
b101000 "
b1 #
