chapter 4/ex1/average_30.vhdl
ENTITY average_30 IS
    PORT (
        samples : IN INTEGER_VECTOR(1 TO 30);
        average : OUT REAL
    );
END ENTITY average_30;

ARCHITECTURE behavioral OF average_30 IS

BEGIN

    compute : PROCESS (samples) IS
        VARIABLE sum : INTEGER;
    BEGIN
        sum := 0;
        FOR i IN samples'RANGE LOOP
            sum := sum + samples(i);
        END LOOP;
        average <= REAL(sum) / 30.0;
    END PROCESS compute;

END ARCHITECTURE;

chapter 4/ex1/test_average_30.vhdl
entity test_average_30 is
end entity test_average_30;

architecture test of test_average_30 is
    signal samples : INTEGER_VECTOR(1 to 30) := (others => 0);
    signal average : REAL := 0.0;
begin

    dut : entity work.average_30(behavioral)
    port map (samples, average);
    
    stimulus : process is
    begin
        samples <= (1, others => 0); wait for 10 ns;
        samples <= (1, 1, 1, others => 0); wait for 10 ns;
        samples <= (others => 1); wait for 10 ns;
        samples <= (15 to 29 => 2, others => (-1)); wait for 10 ns;
    end process stimulus;

end architecture;

chapter 4/ex1/test_average_30.vcd
$date
  Fri Oct 25 10:52:28 2024
$end
$version
  GHDL v0
$end
$timescale
  1 fs
$end
$scope module standard $end
$upscope $end
$scope module test_average_30 $end
$comment samples is not handled $end
$var real 64 ! average $end
$scope module dut $end
$comment samples is not handled $end
$var real 64 " average $end
$upscope $end
$upscope $end
$enddefinitions $end
#0
r3.333333333333333e-2 !
r3.333333333333333e-2 "
#10000000
r1.0e-1 !
r1.0e-1 "
#20000000
r1.0 !
r1.0 "
#30000000
r5.0e-1 !
r5.0e-1 "
#40000000
r3.333333333333333e-2 !
r3.333333333333333e-2 "
#50000000
r1.0e-1 !
r1.0e-1 "
#60000000
r1.0 !
r1.0 "
#70000000
r5.0e-1 !
r5.0e-1 "
#80000000
r3.333333333333333e-2 !
r3.333333333333333e-2 "
#90000000
r1.0e-1 !
r1.0e-1 "
#100000000
r1.0 !
r1.0 "
