chapter 3/ex6&7/exp.vhdl
ENTITY exp IS
    PORT (
        x : IN REAL;
        result : OUT REAL);
END ENTITY exp;

ARCHITECTURE series OF exp IS
BEGIN

    summation : PROCESS (x) IS
        VARIABLE sum, term : REAL;
        VARIABLE n : NATURAL;
    BEGIN
        sum := 1.0;
        term := 1.0;
        n := 0;
        WHILE ABS term > ABS (sum / 104.0) LOOP
            n := n + 1;
            term := term * x / REAL(n);
            sum := sum + term;
        END LOOP;
        result <= sum;
    END PROCESS summation;

END ARCHITECTURE series;

ARCHITECTURE bounded OF exp IS
BEGIN

    summation : PROCESS (x) IS
        VARIABLE sum, term : REAL;
    BEGIN
        sum := 1.0;
        term := 1.0;
        FOR n IN 1 TO 7 LOOP
            term := term * x / REAL(n);
            sum := sum + term;
        END LOOP;
        result <= sum;
    END PROCESS summation;

END ARCHITECTURE bounded;

chapter 3/ex6&7/test_exp.vhdl
entity test_exp is
end entity test_exp;
architecture test of test_exp is
    signal x, s_result, b_result : REAL := 0.0;
begin
    dut_series : entity work.exp(series)
    port map (x, s_result);
    dut_bounded : entity work.exp(bounded)
    port map (x, b_result);
    
    stimulus : process is
    begin
        x <= 1.0; wait for 5 ns;
        x <= 2.0; wait for 5 ns;
        x <= 0.0; wait for 5 ns;
        x <= (-1.0); wait for 5 ns;
        x <= (-3.0); wait for 5 ns;
        x <= 10.0; wait for 5 ns;
    end process stimulus;
end architecture test;

chapter 3/ex6&7/test_exp.vcd
$date
  Thu Oct 24 12:54:29 2024
$end
$version
  GHDL v0
$end
$timescale
  1 fs
$end
$scope module standard $end
$upscope $end
$scope module test_exp $end
$var real 64 ! x $end
$var real 64 " s_result $end
$var real 64 # b_result $end
$scope module dut_series $end
$var real 64 $ x $end
$var real 64 % result $end
$upscope $end
$scope module dut_bounded $end
$var real 64 & x $end
$var real 64 ' result $end
$upscope $end
$upscope $end
$enddefinitions $end
#0
r1.0 !
r2.7166666666666663 "
r2.7182539682539684 #
r1.0 $
r2.7166666666666663 %
r1.0 &
r2.7182539682539684 '
#5000000
r2.0 !
r7.3809523809523805 "
r7.3809523809523805 #
r2.0 $
r7.3809523809523805 %
r2.0 &
r7.3809523809523805 '
#10000000
r0.0 !
r1.0 "
r1.0 #
r0.0 $
r1.0 %
r0.0 &
r1.0 '
#15000000
r-1.0 !
r3.680555555555556e-1 "
r3.678571428571429e-1 #
r-1.0 $
r3.680555555555556e-1 %
r-1.0 &
r3.678571428571429e-1 '
#20000000
r-3.0 !
r4.974143044455552e-2 "
r-7.142857142857134e-2 #
r-3.0 $
r4.974143044455552e-2 %
r-3.0 &
r-7.142857142857134e-2 '
#25000000
r1.0e1 !
r2.1868172496965697e4 "
r4.850682539682539e3 #
r1.0e1 $
r2.1868172496965697e4 %
r1.0e1 &
r4.850682539682539e3 '
#30000000
r1.0 !
r2.7166666666666663 "
r2.7182539682539684 #
r1.0 $
r2.7166666666666663 %
r1.0 &
r2.7182539682539684 '
#35000000
r2.0 !
r7.3809523809523805 "
r7.3809523809523805 #
r2.0 $
r7.3809523809523805 %
r2.0 &
r7.3809523809523805 '
#40000000
r0.0 !
r1.0 "
r1.0 #
r0.0 $
r1.0 %
r0.0 &
r1.0 '
#45000000
r-1.0 !
r3.680555555555556e-1 "
r3.678571428571429e-1 #
r-1.0 $
r3.680555555555556e-1 %
r-1.0 &
r3.678571428571429e-1 '
#50000000
r-3.0 !
r4.974143044455552e-2 "
r-7.142857142857134e-2 #
r-3.0 $
r4.974143044455552e-2 %
r-3.0 &
r-7.142857142857134e-2 '
#55000000
r1.0e1 !
r2.1868172496965697e4 "
r4.850682539682539e3 #
r1.0e1 $
r2.1868172496965697e4 %
r1.0e1 &
r4.850682539682539e3 '
#60000000
r1.0 !
r2.7166666666666663 "
r2.7182539682539684 #
r1.0 $
r2.7166666666666663 %
r1.0 &
r2.7182539682539684 '
#65000000
r2.0 !
r7.3809523809523805 "
r7.3809523809523805 #
r2.0 $
r7.3809523809523805 %
r2.0 &
r7.3809523809523805 '
#70000000
r0.0 !
r1.0 "
r1.0 #
r0.0 $
r1.0 %
r0.0 &
r1.0 '
#75000000
r-1.0 !
r3.680555555555556e-1 "
r3.678571428571429e-1 #
r-1.0 $
r3.680555555555556e-1 %
r-1.0 &
r3.678571428571429e-1 '
#80000000
r-3.0 !
r4.974143044455552e-2 "
r-7.142857142857134e-2 #
r-3.0 $
r4.974143044455552e-2 %
r-3.0 &
r-7.142857142857134e-2 '
#85000000
r1.0e1 !
r2.1868172496965697e4 "
r4.850682539682539e3 #
r1.0e1 $
r2.1868172496965697e4 %
r1.0e1 &
r4.850682539682539e3 '
#90000000
r1.0 !
r2.7166666666666663 "
r2.7182539682539684 #
r1.0 $
r2.7166666666666663 %
r1.0 &
r2.7182539682539684 '
#95000000
r2.0 !
r7.3809523809523805 "
r7.3809523809523805 #
r2.0 $
r7.3809523809523805 %
r2.0 &
r7.3809523809523805 '
#100000000
r0.0 !
r1.0 "
r1.0 #
r0.0 $
r1.0 %
r0.0 &
r1.0 '
