chapter 4/ex10/encoder.vhdl
ENTITY encoder IS
    PORT (
        bytes : IN bit_vector(0 TO 15);
        first : OUT NATURAL RANGE 0 TO 15;
        any : OUT BIT
    );
END ENTITY encoder;

ARCHITECTURE behav OF encoder IS

BEGIN

    search : PROCESS (bytes) IS
        VARIABLE buf : BIT;
    BEGIN

        buf := OR bytes;

        IF buf THEN
            FOR i IN bytes'RANGE LOOP
                IF bytes(i) THEN
                    first <= i;
                    EXIT;
                END IF;
            END LOOP;
        END IF;

        any <= buf;

    END PROCESS search;

END ARCHITECTURE;

chapter 4/ex10/test_encoder.vhdl
ENTITY test_encoder IS
END ENTITY test_encoder;

ARCHITECTURE test OF test_encoder IS
    SIGNAL bytes : bit_vector(0 TO 15);
    SIGNAL first : NATURAL RANGE 0 TO 15;
    SIGNAL any : BIT;
BEGIN

    dut : ENTITY work.encoder(behav)
        PORT MAP(bytes, first, any);

    stimulus : PROCESS IS
    BEGIN

        bytes <= (OTHERS => '0');
        WAIT FOR 5 ns;
        bytes <= ('1', OTHERS => '0');
        WAIT FOR 5 ns;
        bytes <= ('0', OTHERS => '1');
        WAIT FOR 5 ns;
        bytes <= (14 => '1', OTHERS => '0');
        WAIT FOR 5 ns;

    END PROCESS stimulus;

END ARCHITECTURE;

chapter 4/ex10/test_encoder.vcd
$date
  Mon Oct 28 16:29:12 2024
$end
$version
  GHDL v0
$end
$timescale
  1 fs
$end
$scope module standard $end
$upscope $end
$scope module test_encoder $end
$var reg 16 ! bytes[0:15] $end
$var integer 32 " first $end
$var reg 1 # any $end
$scope module dut $end
$var reg 16 $ bytes[0:15] $end
$var integer 32 % first $end
$var reg 1 & any $end
$upscope $end
$upscope $end
$enddefinitions $end
#0
b0000000000000000 !
b0 "
0#
b0000000000000000 $
b0 %
0&
#5000000
b1000000000000000 !
1#
b1000000000000000 $
1&
#10000000
b0111111111111111 !
b1 "
b0111111111111111 $
b1 %
#15000000
b0000000000000010 !
b1110 "
b0000000000000010 $
b1110 %
#20000000
b0000000000000000 !
0#
b0000000000000000 $
0&
#25000000
b1000000000000000 !
b0 "
1#
b1000000000000000 $
b0 %
1&
#30000000
b0111111111111111 !
b1 "
b0111111111111111 $
b1 %
#35000000
b0000000000000010 !
b1110 "
b0000000000000010 $
b1110 %
#40000000
b0000000000000000 !
0#
b0000000000000000 $
0&
#45000000
b1000000000000000 !
b0 "
1#
b1000000000000000 $
b0 %
1&
#50000000
b0111111111111111 !
b1 "
b0111111111111111 $
b1 %
#55000000
b0000000000000010 !
b1110 "
b0000000000000010 $
b1110 %
#60000000
b0000000000000000 !
0#
b0000000000000000 $
0&
#65000000
b1000000000000000 !
b0 "
1#
b1000000000000000 $
b0 %
1&
#70000000
b0111111111111111 !
b1 "
b0111111111111111 $
b1 %
#75000000
b0000000000000010 !
b1110 "
b0000000000000010 $
b1110 %
#80000000
b0000000000000000 !
0#
b0000000000000000 $
0&
#85000000
b1000000000000000 !
b0 "
1#
b1000000000000000 $
b0 %
1&
#90000000
b0111111111111111 !
b1 "
b0111111111111111 $
b1 %
#95000000
b0000000000000010 !
b1110 "
b0000000000000010 $
b1110 %
#100000000
b0000000000000000 !
0#
b0000000000000000 $
0&
