chapter 1/ex10/mux2.vhdl
ENTITY mux2 IS
    PORT (
        a, b, sel : IN BIT;
        z : OUT BIT);
END ENTITY mux2;

ARCHITECTURE behav OF mux2 IS
BEGIN
    selector : PROCESS IS
    BEGIN
        IF sel THEN
            z <= b;
        ELSE
            z <= a;
        END IF;
        WAIT FOR 1 ns;
    END PROCESS selector;
END ARCHITECTURE behav;

chapter 1/ex11/mux2x4.vhdl
ENTITY mux2x4 IS
    PORT (
        a0, a1, a2, a3, b0, b1, b2, b3, sel : IN BIT;
        z0, z1, z2, z3 : OUT BIT);
END ENTITY mux2x4;

ARCHITECTURE struct OF mux2x4 IS
BEGIN
    bit0 : ENTITY work.mux2(behav) PORT MAP (a0, b0, sel, z0);
    bit1 : ENTITY work.mux2(behav) PORT MAP (a1, b1, sel, z1);
    bit2 : ENTITY work.mux2(behav) PORT MAP (a2, b2, sel, z2);
    bit3 : ENTITY work.mux2(behav) PORT MAP (a3, b3, sel, z3);
END ARCHITECTURE struct;

chapter 1/ex11/test_mux2x4.vhdl
entity test_mux2x4 is
end entity test_mux2x4;

architecture test of test_mux2x4 is
    signal a0, a1, a2, a3, b0, b1, b2, b3, sel, z0, z1, z2, z3 : bit;
begin
    dut : entity work.mux2x4(struct)
    port map (a0, a1, a2, a3, b0, b1, b2, b3, sel, z0, z1, z2, z3);
    stimulus : process is
    begin
        a0 <= '1'; a1 <= '0'; a2 <= '1'; a3 <= '1';
        b0 <= '0'; b1 <= '1'; b2 <= '1'; b3 <= '0';
        sel <= '0'; wait for 20 ns;
        sel <= '1'; wait for 20 ns;
        a0 <= '0'; a1 <= '0'; a2 <= '0'; a3 <= '0';
        b0 <= '1'; b1 <= '1'; b2 <= '1'; b3 <= '1';
        sel <= '0'; wait for 20 ns;
        sel <= '1'; wait for 20 ns;
        wait;
    end process stimulus;
end architecture test;

chapter 1/ex11/test_mux2x4.vcd
$date
  Wed Oct 23 11:08:03 2024
$end
$version
  GHDL v0
$end
$timescale
  1 fs
$end
$scope module standard $end
$upscope $end
$scope module test_mux2x4 $end
$var reg 1 ! a0 $end
$var reg 1 " a1 $end
$var reg 1 # a2 $end
$var reg 1 $ a3 $end
$var reg 1 % b0 $end
$var reg 1 & b1 $end
$var reg 1 ' b2 $end
$var reg 1 ( b3 $end
$var reg 1 ) sel $end
$var reg 1 * z0 $end
$var reg 1 + z1 $end
$var reg 1 , z2 $end
$var reg 1 - z3 $end
$scope module dut $end
$var reg 1 . a0 $end
$var reg 1 / a1 $end
$var reg 1 0 a2 $end
$var reg 1 1 a3 $end
$var reg 1 2 b0 $end
$var reg 1 3 b1 $end
$var reg 1 4 b2 $end
$var reg 1 5 b3 $end
$var reg 1 6 sel $end
$var reg 1 7 z0 $end
$var reg 1 8 z1 $end
$var reg 1 9 z2 $end
$var reg 1 : z3 $end
$scope module bit0 $end
$var reg 1 ; a $end
$var reg 1 < b $end
$var reg 1 = sel $end
$var reg 1 > z $end
$upscope $end
$scope module bit1 $end
$var reg 1 ? a $end
$var reg 1 @ b $end
$var reg 1 A sel $end
$var reg 1 B z $end
$upscope $end
$scope module bit2 $end
$var reg 1 C a $end
$var reg 1 D b $end
$var reg 1 E sel $end
$var reg 1 F z $end
$upscope $end
$scope module bit3 $end
$var reg 1 G a $end
$var reg 1 H b $end
$var reg 1 I sel $end
$var reg 1 J z $end
$upscope $end
$upscope $end
$upscope $end
$enddefinitions $end
#0
1!
0"
1#
1$
0%
1&
1'
0(
0)
0*
0+
0,
0-
1.
0/
10
11
02
13
14
05
06
07
08
09
0:
1;
0<
0=
0>
0?
1@
0A
0B
1C
1D
0E
0F
1G
0H
0I
0J
#1000000
1*
1,
1-
17
19
1:
1>
1F
1J
#2000000
#3000000
#4000000
#5000000
#6000000
#7000000
#8000000
#9000000
#10000000
#11000000
#12000000
#13000000
#14000000
#15000000
#16000000
#17000000
#18000000
#19000000
#20000000
1)
16
1=
1A
1E
1I
#21000000
0*
1+
0-
07
18
0:
0>
1B
0J
#22000000
#23000000
#24000000
#25000000
#26000000
#27000000
#28000000
#29000000
#30000000
#31000000
#32000000
#33000000
#34000000
#35000000
#36000000
#37000000
#38000000
#39000000
#40000000
0!
0#
0$
1%
1(
0)
0.
00
01
12
15
06
0;
1<
0=
0A
0C
0E
0G
1H
0I
#41000000
0+
0,
08
09
0B
0F
#42000000
#43000000
#44000000
#45000000
#46000000
#47000000
#48000000
#49000000
#50000000
#51000000
#52000000
#53000000
#54000000
#55000000
#56000000
#57000000
#58000000
#59000000
#60000000
1)
16
1=
1A
1E
1I
#61000000
1*
1+
1,
1-
17
18
19
1:
1>
1B
1F
1J
