chapter 3/ex12&13/counter16.vhdl
PACKAGE int_types IS
    TYPE count16 IS RANGE 15 DOWNTO 0;
    TYPE count21 IS RANGE 20 DOWNTO 0;
END PACKAGE int_types;

USE work.int_types.count16;

ENTITY count_down_16 IS
    PORT (
        clk, load : IN BIT;
        data : IN count16;
        counter : OUT count16
    );
END ENTITY count_down_16;

ARCHITECTURE behav OF count_down_16 IS
BEGIN

    procceed : PROCESS (clk) IS
        VARIABLE count : count16 := 15;
    BEGIN

        IF load THEN
            count := data;
        ELSE
            count := count16'rightof(count) WHEN RISING_EDGE(clk) AND count /= 0
        ELSE 15 WHEN RISING_EDGE(clk);
        END IF;
        counter <= count;

    END PROCESS procceed;
END ARCHITECTURE behav;

chapter 3/ex12&13/test_counter16.vhdl
entity test_counter16 is 
end entity test_counter16;

use work.int_types.all;

architecture test_count of test_counter16 is
    signal clk, load : bit := '0';
    signal counter, data : count16 := 15;
begin
    dut : entity work.count_down_16(behav)
    port map (clk, load, data, counter);
    stimulus : process is
    begin
        for n in count21 loop
            clk <= '0'; wait for 5 ns;
            clk <= '1'; wait for 5 ns;
            load <= '0' when n = 20;
        end loop;
        clk <= '0'; wait for 2 ns;
        load <= '1';
        data <= 6; wait for 3 ns;
        clk <= '1'; wait for 5 ns;
    end process stimulus;
end architecture test_count;

chapter 3/ex12&13/test_counter16.vcd
$date
  Thu Oct 24 16:02:24 2024
$end
$version
  GHDL v0
$end
$timescale
  1 fs
$end
$scope module standard $end
$upscope $end
$scope module int_types $end
$upscope $end
$scope module test_counter16 $end
$var reg 1 ! clk $end
$var reg 1 " load $end
$var integer 32 # counter $end
$var integer 32 $ data $end
$scope module dut $end
$var reg 1 % clk $end
$var reg 1 & load $end
$var integer 32 ' data $end
$var integer 32 ( counter $end
$upscope $end
$upscope $end
$enddefinitions $end
#0
0!
0"
b1111 #
b1111 $
0%
0&
b1111 '
b1111 (
#5000000
1!
b1110 #
1%
b1110 (
#10000000
0!
0%
#15000000
1!
b1101 #
1%
b1101 (
#20000000
0!
0%
#25000000
1!
b1100 #
1%
b1100 (
#30000000
0!
0%
#35000000
1!
b1011 #
1%
b1011 (
#40000000
0!
0%
#45000000
1!
b1010 #
1%
b1010 (
#50000000
0!
0%
#55000000
1!
b1001 #
1%
b1001 (
#60000000
0!
0%
#65000000
1!
b1000 #
1%
b1000 (
#70000000
0!
0%
#75000000
1!
b111 #
1%
b111 (
#80000000
0!
0%
#85000000
1!
b110 #
1%
b110 (
#90000000
0!
0%
#95000000
1!
b101 #
1%
b101 (
#100000000
0!
0%
#105000000
1!
b100 #
1%
b100 (
#110000000
0!
0%
#115000000
1!
b11 #
1%
b11 (
#120000000
0!
0%
#125000000
1!
b10 #
1%
b10 (
#130000000
0!
0%
#135000000
1!
b1 #
1%
b1 (
#140000000
0!
0%
#145000000
1!
b0 #
1%
b0 (
#150000000
0!
0%
#155000000
1!
b1111 #
1%
b1111 (
#160000000
0!
0%
#165000000
1!
b1110 #
1%
b1110 (
#170000000
0!
0%
#175000000
1!
b1101 #
1%
b1101 (
#180000000
0!
0%
#185000000
1!
b1100 #
1%
b1100 (
#190000000
0!
0%
#195000000
1!
b1011 #
1%
b1011 (
#200000000
0!
0%
#205000000
1!
b1010 #
1%
b1010 (
#210000000
0!
0%
#212000000
1"
b110 $
1&
b110 '
#215000000
1!
b110 #
1%
b110 (
#220000000
0!
0%
#225000000
1!
1%
#230000000
0!
0"
0%
0&
#235000000
1!
b101 #
1%
b101 (
#240000000
0!
0%
#245000000
1!
b100 #
1%
b100 (
#250000000
0!
0%
#255000000
1!
b11 #
1%
b11 (
#260000000
0!
0%
#265000000
1!
b10 #
1%
b10 (
#270000000
0!
0%
#275000000
1!
b1 #
1%
b1 (
#280000000
0!
0%
#285000000
1!
b0 #
1%
b0 (
#290000000
0!
0%
#295000000
1!
b1111 #
1%
b1111 (
#300000000
0!
0%
#305000000
1!
b1110 #
1%
b1110 (
#310000000
0!
0%
#315000000
1!
b1101 #
1%
b1101 (
#320000000
0!
0%
#325000000
1!
b1100 #
1%
b1100 (
#330000000
0!
0%
#335000000
1!
b1011 #
1%
b1011 (
#340000000
0!
0%
#345000000
1!
b1010 #
1%
b1010 (
#350000000
0!
0%
#355000000
1!
b1001 #
1%
b1001 (
#360000000
0!
0%
#365000000
1!
b1000 #
1%
b1000 (
#370000000
0!
0%
#375000000
1!
b111 #
1%
b111 (
#380000000
0!
0%
#385000000
1!
b110 #
1%
b110 (
#390000000
0!
0%
#395000000
1!
b101 #
1%
b101 (
#400000000
0!
0%
#405000000
1!
b100 #
1%
b100 (
#410000000
0!
0%
#415000000
1!
b11 #
1%
b11 (
#420000000
0!
0%
#425000000
1!
b10 #
1%
b10 (
#430000000
0!
0%
#432000000
1"
1&
#435000000
1!
b110 #
1%
b110 (
#440000000
0!
0%
#445000000
1!
1%
#450000000
0!
0"
0%
0&
#455000000
1!
b101 #
1%
b101 (
#460000000
0!
0%
#465000000
1!
b100 #
1%
b100 (
#470000000
0!
0%
#475000000
1!
b11 #
1%
b11 (
#480000000
0!
0%
#485000000
1!
b10 #
1%
b10 (
#490000000
0!
0%
#495000000
1!
b1 #
1%
b1 (
#500000000
0!
0%
#505000000
1!
b0 #
1%
b0 (
#510000000
0!
0%
#515000000
1!
b1111 #
1%
b1111 (
#520000000
0!
0%
#525000000
1!
b1110 #
1%
b1110 (
#530000000
0!
0%
#535000000
1!
b1101 #
1%
b1101 (
#540000000
0!
0%
#545000000
1!
b1100 #
1%
b1100 (
#550000000
0!
0%
#555000000
1!
b1011 #
1%
b1011 (
#560000000
0!
0%
#565000000
1!
b1010 #
1%
b1010 (
#570000000
0!
0%
#575000000
1!
b1001 #
1%
b1001 (
#580000000
0!
0%
#585000000
1!
b1000 #
1%
b1000 (
#590000000
0!
0%
#595000000
1!
b111 #
1%
b111 (
#600000000
0!
0%
#605000000
1!
b110 #
1%
b110 (
#610000000
0!
0%
#615000000
1!
b101 #
1%
b101 (
#620000000
0!
0%
#625000000
1!
b100 #
1%
b100 (
#630000000
0!
0%
#635000000
1!
b11 #
1%
b11 (
#640000000
0!
0%
#645000000
1!
b10 #
1%
b10 (
#650000000
0!
0%
#652000000
1"
1&
#655000000
1!
b110 #
1%
b110 (
#660000000
0!
0%
#665000000
1!
1%
#670000000
0!
0"
0%
0&
#675000000
1!
b101 #
1%
b101 (
#680000000
0!
0%
#685000000
1!
b100 #
1%
b100 (
#690000000
0!
0%
#695000000
1!
b11 #
1%
b11 (
#700000000
0!
0%
#705000000
1!
b10 #
1%
b10 (
#710000000
0!
0%
#715000000
1!
b1 #
1%
b1 (
#720000000
0!
0%
#725000000
1!
b0 #
1%
b0 (
#730000000
0!
0%
#735000000
1!
b1111 #
1%
b1111 (
#740000000
0!
0%
#745000000
1!
b1110 #
1%
b1110 (
#750000000
0!
0%
#755000000
1!
b1101 #
1%
b1101 (
#760000000
0!
0%
#765000000
1!
b1100 #
1%
b1100 (
#770000000
0!
0%
#775000000
1!
b1011 #
1%
b1011 (
#780000000
0!
0%
#785000000
1!
b1010 #
1%
b1010 (
#790000000
0!
0%
#795000000
1!
b1001 #
1%
b1001 (
#800000000
0!
0%
#805000000
1!
b1000 #
1%
b1000 (
#810000000
0!
0%
#815000000
1!
b111 #
1%
b111 (
#820000000
0!
0%
#825000000
1!
b110 #
1%
b110 (
#830000000
0!
0%
#835000000
1!
b101 #
1%
b101 (
#840000000
0!
0%
#845000000
1!
b100 #
1%
b100 (
#850000000
0!
0%
#855000000
1!
b11 #
1%
b11 (
#860000000
0!
0%
#865000000
1!
b10 #
1%
b10 (
#870000000
0!
0%
#872000000
1"
1&
#875000000
1!
b110 #
1%
b110 (
#880000000
0!
0%
#885000000
1!
1%
#890000000
0!
0"
0%
0&
#895000000
1!
b101 #
1%
b101 (
#900000000
0!
0%
#905000000
1!
b100 #
1%
b100 (
#910000000
0!
0%
#915000000
1!
b11 #
1%
b11 (
#920000000
0!
0%
#925000000
1!
b10 #
1%
b10 (
#930000000
0!
0%
#935000000
1!
b1 #
1%
b1 (
#940000000
0!
0%
#945000000
1!
b0 #
1%
b0 (
#950000000
0!
0%
#955000000
1!
b1111 #
1%
b1111 (
#960000000
0!
0%
#965000000
1!
b1110 #
1%
b1110 (
#970000000
0!
0%
#975000000
1!
b1101 #
1%
b1101 (
#980000000
0!
0%
#985000000
1!
b1100 #
1%
b1100 (
#990000000
0!
0%
#995000000
1!
b1011 #
1%
b1011 (
