chapter 4/ex7/repack8to32a.vhdl
ENTITY repack8to32a IS
    PORT (
        v1 : IN bit_vector(0 TO 7);
        v2 : OUT bit_vector(0 TO 31)
    );
END ENTITY repack8to32a;

ARCHITECTURE cycle OF repack8to32a IS
BEGIN
    place_and_shift : PROCESS (v1) IS
        VARIABLE v : bit_vector(0 TO 31);
    BEGIN
        -- Initialize v with all zeros
        v := (OTHERS => '0');

        -- Assign v1 to the upper part of v
        FOR i IN v1'RANGE LOOP
            v(i + 24) := v1(i);
        END LOOP;

        -- Perform arithmetic fill left by 24 bits
        v(0 TO 24) := (OTHERS => v1(0));

        v2 <= v;
    END PROCESS place_and_shift;
END ARCHITECTURE cycle;

chapter 4/ex7/test_repack.vhdl
entity test_repack is
end entity test_repack;

architecture test of test_repack is
    signal v1 : BIT_VECTOR(0 to 7);
    signal v2 : BIT_VECTOR(0 to 31);
begin

    dut : entity work.repack8to32a(cycle)
    port map (v1, v2);
    
    stimulus : process is
    begin
        v1 <= (others => '1'); wait for 5 ns;
        v1 <= ('0', others => '1'); wait for 5 ns;
        v1 <= (others => '0'); wait for 5 ns;
        v1 <= ('1', '1', '1', others => '0'); wait for 5 ns;
    end process stimulus;

end architecture;

chapter 4/ex7/test_repack.vcd
$date
  Fri Oct 25 21:48:52 2024
$end
$version
  GHDL v0
$end
$timescale
  1 fs
$end
$scope module standard $end
$upscope $end
$scope module test_repack $end
$var reg 8 ! v1[0:7] $end
$var reg 32 " v2[0:31] $end
$scope module dut $end
$var reg 8 # v1[0:7] $end
$var reg 32 $ v2[0:31] $end
$upscope $end
$upscope $end
$enddefinitions $end
#0
b11111111 !
b11111111111111111111111111111111 "
b11111111 #
b11111111111111111111111111111111 $
#5000000
b01111111 !
b00000000000000000000000001111111 "
b01111111 #
b00000000000000000000000001111111 $
#10000000
b00000000 !
b00000000000000000000000000000000 "
b00000000 #
b00000000000000000000000000000000 $
#15000000
b11100000 !
b11111111111111111111111111100000 "
b11100000 #
b11111111111111111111111111100000 $
#20000000
b11111111 !
b11111111111111111111111111111111 "
b11111111 #
b11111111111111111111111111111111 $
#25000000
b01111111 !
b00000000000000000000000001111111 "
b01111111 #
b00000000000000000000000001111111 $
#30000000
b00000000 !
b00000000000000000000000000000000 "
b00000000 #
b00000000000000000000000000000000 $
#35000000
b11100000 !
b11111111111111111111111111100000 "
b11100000 #
b11111111111111111111111111100000 $
#40000000
b11111111 !
b11111111111111111111111111111111 "
b11111111 #
b11111111111111111111111111111111 $
#45000000
b01111111 !
b00000000000000000000000001111111 "
b01111111 #
b00000000000000000000000001111111 $
#50000000
b00000000 !
b00000000000000000000000000000000 "
b00000000 #
b00000000000000000000000000000000 $
#55000000
b11100000 !
b11111111111111111111111111100000 "
b11100000 #
b11111111111111111111111111100000 $
#60000000
b11111111 !
b11111111111111111111111111111111 "
b11111111 #
b11111111111111111111111111111111 $
#65000000
b01111111 !
b00000000000000000000000001111111 "
b01111111 #
b00000000000000000000000001111111 $
#70000000
b00000000 !
b00000000000000000000000000000000 "
b00000000 #
b00000000000000000000000000000000 $
#75000000
b11100000 !
b11111111111111111111111111100000 "
b11100000 #
b11111111111111111111111111100000 $
#80000000
b11111111 !
b11111111111111111111111111111111 "
b11111111 #
b11111111111111111111111111111111 $
#85000000
b01111111 !
b00000000000000000000000001111111 "
b01111111 #
b00000000000000000000000001111111 $
#90000000
b00000000 !
b00000000000000000000000000000000 "
b00000000 #
b00000000000000000000000000000000 $
#95000000
b11100000 !
b11111111111111111111111111100000 "
b11100000 #
b11111111111111111111111111100000 $
#100000000
b11111111 !
b11111111111111111111111111111111 "
b11111111 #
b11111111111111111111111111111111 $
