chapter 3/ex11/float_ALU.vhdl
ENTITY floating_ALU IS
    PORT (
        x, y : IN REAL;
        f0, f1 : IN BIT;
        z : OUT REAL
    );
END ENTITY floating_ALU;

ARCHITECTURE behav OF floating_ALU IS
BEGIN

    alu : PROCESS (x, y, f0, f1) IS
        VARIABLE result : REAL;
    BEGIN

        result := x + y WHEN NOT f0 AND NOT f1
    ELSE x - y WHEN f0 AND NOT f1
    ELSE x * y WHEN NOT f0 AND f1
    ELSE x / y WHEN y /= 0.0
    ELSE REAL'HIGH;

        z <= result;

    END PROCESS alu;

END ARCHITECTURE behav;

chapter 3/ex11/test_float_ALU.vhdl
entity test_float_ALU is
end entity test_float_ALU;

architecture test of test_float_ALU is
    signal x, y, z : real := 0.0;
    signal f0, f1 : bit := '0';
begin
    dut : entity work.floating_ALU(behav)
    port map (x, y, f0, f1, z);
    stimulus : process is
    begin
        x <= 2.0; y <= 3.0; wait for 10 ns;
        f0 <= '1'; wait for 10 ns;
        f1 <= '1'; wait for 10 ns;
        f0 <= '0'; wait for 10 ns;
        x <= 1.0; y <= 0.0;
        f1 <= '0'; wait for 10 ns;
        f0 <= '1'; wait for 10 ns;
        f1 <= '1'; wait for 10 ns;
        f0 <= '0'; wait for 10 ns;
        x <= 0.0; y <= 1.0;
        f1 <= '0'; wait for 10 ns;
        f0 <= '1'; wait for 10 ns;
        f1 <= '1'; wait for 10 ns;
        f0 <= '0'; wait for 10 ns;
        wait;
    end process stimulus;
end architecture test;

chapter 3/ex11/test_float_ALU.vcd
$date
  Thu Oct 24 15:46:52 2024
$end
$version
  GHDL v0
$end
$timescale
  1 fs
$end
$scope module standard $end
$upscope $end
$scope module test_float_alu $end
$var real 64 ! x $end
$var real 64 " y $end
$var real 64 # z $end
$var reg 1 $ f0 $end
$var reg 1 % f1 $end
$scope module dut $end
$var real 64 & x $end
$var real 64 ' y $end
$var reg 1 ( f0 $end
$var reg 1 ) f1 $end
$var real 64 * z $end
$upscope $end
$upscope $end
$enddefinitions $end
#0
r2.0 !
r3.0 "
r5.0 #
0$
0%
r2.0 &
r3.0 '
0(
0)
r5.0 *
#10000000
r-1.0 #
1$
1(
r-1.0 *
#20000000
r6.666666666666666e-1 #
1%
1)
r6.666666666666666e-1 *
#30000000
r6.0 #
0$
0(
r6.0 *
#40000000
r1.0 !
r0.0 "
r1.0 #
0%
r1.0 &
r0.0 '
0)
r1.0 *
#50000000
1$
1(
#60000000
r1.7976931348623157e308 #
1%
1)
r1.7976931348623157e308 *
#70000000
r0.0 #
0$
0(
r0.0 *
#80000000
r0.0 !
r1.0 "
r1.0 #
0%
r0.0 &
r1.0 '
0)
r1.0 *
#90000000
r-1.0 #
1$
1(
r-1.0 *
#100000000
r0.0 #
1%
1)
r0.0 *
