chapter 4/ex2/std_ulogic_to_bit_vector.vhdl
library ieee;
use ieee.std_logic_1164.all;

entity vector_std_ulogic_to_bit is
    port (
        v1 : in std_ulogic_vector;
        v2 : out bit_vector
    );
end entity vector_std_ulogic_to_bit;

architecture behav of vector_std_ulogic_to_bit is
    type std_ulogic_to_bit_type is array (std_ulogic) of bit;
begin
    
    mapping : process (v1) is
        constant std_ulogic_to_bit : std_ulogic_to_bit_type := (
            '1' | 'H' => '1',
            others => '0'
        );
        variable v : bit_vector(v1'range);
    begin
        for i in v1'range loop
            v(i) := std_ulogic_to_bit(v1(i));
        end loop;
        v2 <= v;
    end process mapping;
end architecture behav;

chapter 4/ex2/test_std_ulogic_to_bit_vector.vhdl
ENTITY test_std_ulogic_to_bit_vector IS
END ENTITY test_std_ulogic_to_bit_vector;

LIBRARY ieee;
USE ieee.std_logic_1164.ALL;

ARCHITECTURE test OF test_std_ulogic_to_bit_vector IS
    SIGNAL v1 : STD_ULOGIC_VECTOR(0 TO 15) := (OTHERS => '-');
    SIGNAL v2 : bit_vector(0 TO 15) := (OTHERS => '0');
BEGIN

    dut : ENTITY work.vector_std_ulogic_to_bit(behav)
    PORT MAP(v1, v2);

    stimulus : PROCESS IS
    BEGIN
        v1 <= ('U', '0', '1', 'L', 'H', 'X', 'W', 'Z', OTHERS => '-');
        WAIT FOR 10 ns;
        v1 <= (OTHERS => 'X');
        WAIT FOR 10 ns;
        v1 <= (OTHERS => 'H');
        WAIT FOR 10 ns;
        v1 <= (OTHERS => '1');
        WAIT FOR 10 ns;
        v1 <= (OTHERS => '0');
        WAIT FOR 10 ns;
    END PROCESS stimulus;

END ARCHITECTURE;

chapter 4/ex2/test_std_ulogic_to_bit_vector.vcd
$date
  Fri Oct 25 11:53:18 2024
$end
$version
  GHDL v0
$end
$timescale
  1 fs
$end
$scope module standard $end
$upscope $end
$scope module textio $end
$upscope $end
$scope module std_logic_1164 $end
$upscope $end
$scope module test_std_ulogic_to_bit_vector $end
$var reg 16 ! v1[0:15] $end
$var reg 16 " v2[0:15] $end
$scope module dut $end
$var reg 16 # v1[0:15] $end
$var reg 16 $ v2[0:15] $end
$upscope $end
$upscope $end
$enddefinitions $end
#0
bU01LHXWZ-------- !
b0010100000000000 "
bU01LHXWZ-------- #
b0010100000000000 $
#10000000
bXXXXXXXXXXXXXXXX !
b0000000000000000 "
bXXXXXXXXXXXXXXXX #
b0000000000000000 $
#20000000
bHHHHHHHHHHHHHHHH !
b1111111111111111 "
bHHHHHHHHHHHHHHHH #
b1111111111111111 $
#30000000
b1111111111111111 !
b1111111111111111 #
#40000000
b0000000000000000 !
b0000000000000000 "
b0000000000000000 #
b0000000000000000 $
#50000000
bU01LHXWZ-------- !
b0010100000000000 "
bU01LHXWZ-------- #
b0010100000000000 $
#60000000
bXXXXXXXXXXXXXXXX !
b0000000000000000 "
bXXXXXXXXXXXXXXXX #
b0000000000000000 $
#70000000
bHHHHHHHHHHHHHHHH !
b1111111111111111 "
bHHHHHHHHHHHHHHHH #
b1111111111111111 $
#80000000
b1111111111111111 !
b1111111111111111 #
#90000000
b0000000000000000 !
b0000000000000000 "
b0000000000000000 #
b0000000000000000 $
#100000000
bU01LHXWZ-------- !
b0010100000000000 "
bU01LHXWZ-------- #
b0010100000000000 $
