chapter 4/ex11/maximum.vhdl
ENTITY maximum IS
    PORT (
        sample : IN integer_vector;
        max : OUT INTEGER
    );
END ENTITY maximum;

ARCHITECTURE behav OF maximum IS
BEGIN

    find : PROCESS (sample) IS
        VARIABLE partial_max : INTEGER;
    BEGIN

        partial_max := INTEGER'low;

        FOR i IN sample'RANGE LOOP
            IF sample(i) > partial_max THEN
                partial_max := sample(i);
            END IF;
        END LOOP;
        
        max <= partial_max;

    END PROCESS find;

END ARCHITECTURE;

chapter 4/ex11/test_maximum.vhdl
ENTITY test_maximum IS
END ENTITY test_maximum;

ARCHITECTURE test OF test_maximum IS
    SIGNAL sample0 : integer_vector(1 TO 0);
    SIGNAL sample15 : integer_vector(0 TO 15);
    SIGNAL null_max : INTEGER;
    SIGNAL max : INTEGER;
BEGIN

    null_dut : ENTITY work.maximum(behav)
        PORT MAP(sample0, null_max);

    dut : ENTITY work.maximum(behav)
        PORT MAP(sample15, max);

    stimulus : PROCESS IS
    BEGIN

        sample15 <= (0, 0, 0, OTHERS => 1);
        WAIT FOR 5 ns;

        sample15 <= (31, 20, OTHERS => 0);
        WAIT FOR 5 ns;

        sample15 <= (3, 1, 21, 15, 40, 1, (-1), 12, OTHERS => 0);
        WAIT FOR 5 ns;

        sample15 <= ((-1), OTHERS => (-2));
        WAIT FOR 5 ns;

    END PROCESS stimulus;

END ARCHITECTURE;

chapter 4/ex11/test_maximum.vcd
$date
  Mon Oct 28 18:41:59 2024
$end
$version
  GHDL v0
$end
$timescale
  1 fs
$end
$scope module standard $end
$upscope $end
$scope module test_maximum $end
$comment sample0 is not handled $end
$comment sample15 is not handled $end
$var integer 32 ! null_max $end
$var integer 32 " max $end
$scope module null_dut $end
$comment sample is not handled $end
$var integer 32 # max $end
$upscope $end
$scope module dut $end
$comment sample is not handled $end
$var integer 32 $ max $end
$upscope $end
$upscope $end
$enddefinitions $end
#0
b10000000000000000000000000000000 !
b1 "
b10000000000000000000000000000000 #
b1 $
#5000000
b11111 "
b11111 $
#10000000
b101000 "
b101000 $
#15000000
b11111111111111111111111111111111 "
b11111111111111111111111111111111 $
#20000000
b1 "
b1 $
#25000000
b11111 "
b11111 $
#30000000
b101000 "
b101000 $
#35000000
b11111111111111111111111111111111 "
b11111111111111111111111111111111 $
#40000000
b1 "
b1 $
#45000000
b11111 "
b11111 $
#50000000
b101000 "
b101000 $
