chapter 3/ex14/average16.vhdl
ENTITY average16 IS
    PORT (
        clk : IN BIT;
        datum : IN REAL;
        average : OUT REAL
    );
END ENTITY average16;

ARCHITECTURE behav OF average16 IS
    subtype index is integer range 16 downto 0;
BEGIN

    averaging : PROCESS (clk) IS
        VARIABLE sum : REAL := 0.0;
        VARIABLE count : index;
    BEGIN

        IF count = 0 THEN
            average <= sum / 16.0;
            sum := 0.0;
            count := 16;
        END IF;

        IF RISING_EDGE(clk) THEN
            sum := sum + datum;
            count := index'rightof(count);
        END IF;

    END PROCESS averaging;
END ARCHITECTURE behav;

chapter 3/ex14/test_average16.vhdl
entity test_average16 is
end entity test_average16;

architecture test of test_average16 is
    signal clk : BIT := '0';
    signal datum, average : REAL := 0.0;
begin
    
    dut : entity work.average16(behav)
    port map (clk, datum, average);
    stimulus : process is
        variable datum_l : REAL;
    begin
        clk <= '0'; wait for 5 ns;
        clk <= '1'; wait for 5 ns;
        datum_l := datum + 1.0;
        datum <= datum_l;
        
    end process stimulus;
end architecture test;

chapter 3/ex14/test_average16.vcd
$date
  Thu Oct 24 16:19:45 2024
$end
$version
  GHDL v0
$end
$timescale
  1 fs
$end
$scope module standard $end
$upscope $end
$scope module test_average16 $end
$var reg 1 ! clk $end
$var real 64 " datum $end
$var real 64 # average $end
$scope module dut $end
$var reg 1 $ clk $end
$var real 64 % datum $end
$var real 64 & average $end
$upscope $end
$upscope $end
$enddefinitions $end
#0
0!
r0.0 "
r-1.7976931348623157e308 #
0$
r0.0 %
r-1.7976931348623157e308 &
#5000000
1!
1$
#10000000
0!
r1.0 "
0$
r1.0 %
#15000000
1!
1$
#20000000
0!
r2.0 "
0$
r2.0 %
#25000000
1!
1$
#30000000
0!
r3.0 "
0$
r3.0 %
#35000000
1!
1$
#40000000
0!
r4.0 "
0$
r4.0 %
#45000000
1!
1$
#50000000
0!
r5.0 "
0$
r5.0 %
#55000000
1!
1$
#60000000
0!
r6.0 "
0$
r6.0 %
#65000000
1!
1$
#70000000
0!
r7.0 "
0$
r7.0 %
#75000000
1!
1$
#80000000
0!
r8.0 "
0$
r8.0 %
#85000000
1!
1$
#90000000
0!
r9.0 "
0$
r9.0 %
#95000000
1!
1$
#100000000
0!
r1.0e1 "
0$
r1.0e1 %
#105000000
1!
1$
#110000000
0!
r1.1e1 "
0$
r1.1e1 %
#115000000
1!
1$
#120000000
0!
r1.2e1 "
0$
r1.2e1 %
#125000000
1!
1$
#130000000
0!
r1.3e1 "
0$
r1.3e1 %
#135000000
1!
1$
#140000000
0!
r1.4e1 "
0$
r1.4e1 %
#145000000
1!
1$
#150000000
0!
r1.5e1 "
0$
r1.5e1 %
#155000000
1!
1$
#160000000
0!
r1.6e1 "
r7.5 #
0$
r1.6e1 %
r7.5 &
#165000000
1!
1$
#170000000
0!
r1.7e1 "
0$
r1.7e1 %
#175000000
1!
1$
#180000000
0!
r1.8e1 "
0$
r1.8e1 %
#185000000
1!
1$
#190000000
0!
r1.9e1 "
0$
r1.9e1 %
#195000000
1!
1$
#200000000
0!
r2.0e1 "
0$
r2.0e1 %
#205000000
1!
1$
#210000000
0!
r2.1e1 "
0$
r2.1e1 %
#215000000
1!
1$
#220000000
0!
r2.2e1 "
0$
r2.2e1 %
#225000000
1!
1$
#230000000
0!
r2.3e1 "
0$
r2.3e1 %
#235000000
1!
1$
#240000000
0!
r2.4e1 "
0$
r2.4e1 %
#245000000
1!
1$
#250000000
0!
r2.5e1 "
0$
r2.5e1 %
#255000000
1!
1$
#260000000
0!
r2.6e1 "
0$
r2.6e1 %
#265000000
1!
1$
#270000000
0!
r2.7e1 "
0$
r2.7e1 %
#275000000
1!
1$
#280000000
0!
r2.8e1 "
0$
r2.8e1 %
#285000000
1!
1$
#290000000
0!
r2.9e1 "
0$
r2.9e1 %
#295000000
1!
1$
#300000000
0!
r3.0e1 "
0$
r3.0e1 %
#305000000
1!
1$
#310000000
0!
r3.1e1 "
0$
r3.1e1 %
#315000000
1!
1$
#320000000
0!
r3.2e1 "
r2.35e1 #
0$
r3.2e1 %
r2.35e1 &
#325000000
1!
1$
#330000000
0!
r3.3e1 "
0$
r3.3e1 %
#335000000
1!
1$
#340000000
0!
r3.4e1 "
0$
r3.4e1 %
#345000000
1!
1$
#350000000
0!
r3.5e1 "
0$
r3.5e1 %
#355000000
1!
1$
#360000000
0!
r3.6e1 "
0$
r3.6e1 %
#365000000
1!
1$
#370000000
0!
r3.7e1 "
0$
r3.7e1 %
#375000000
1!
1$
#380000000
0!
r3.8e1 "
0$
r3.8e1 %
#385000000
1!
1$
#390000000
0!
r3.9e1 "
0$
r3.9e1 %
#395000000
1!
1$
#400000000
0!
r4.0e1 "
0$
r4.0e1 %
#405000000
1!
1$
#410000000
0!
r4.1e1 "
0$
r4.1e1 %
#415000000
1!
1$
#420000000
0!
r4.2e1 "
0$
r4.2e1 %
#425000000
1!
1$
#430000000
0!
r4.3e1 "
0$
r4.3e1 %
#435000000
1!
1$
#440000000
0!
r4.4e1 "
0$
r4.4e1 %
#445000000
1!
1$
#450000000
0!
r4.5e1 "
0$
r4.5e1 %
#455000000
1!
1$
#460000000
0!
r4.6e1 "
0$
r4.6e1 %
#465000000
1!
1$
#470000000
0!
r4.7e1 "
0$
r4.7e1 %
#475000000
1!
1$
#480000000
0!
r4.8e1 "
r3.95e1 #
0$
r4.8e1 %
r3.95e1 &
#485000000
1!
1$
#490000000
0!
r4.9e1 "
0$
r4.9e1 %
#495000000
1!
1$
#500000000
0!
r5.0e1 "
0$
r5.0e1 %
#505000000
1!
1$
#510000000
0!
r5.1e1 "
0$
r5.1e1 %
#515000000
1!
1$
#520000000
0!
r5.2e1 "
0$
r5.2e1 %
#525000000
1!
1$
#530000000
0!
r5.3e1 "
0$
r5.3e1 %
#535000000
1!
1$
#540000000
0!
r5.4e1 "
0$
r5.4e1 %
#545000000
1!
1$
#550000000
0!
r5.5e1 "
0$
r5.5e1 %
#555000000
1!
1$
#560000000
0!
r5.6e1 "
0$
r5.6e1 %
#565000000
1!
1$
#570000000
0!
r5.7e1 "
0$
r5.7e1 %
#575000000
1!
1$
#580000000
0!
r5.8e1 "
0$
r5.8e1 %
#585000000
1!
1$
#590000000
0!
r5.9e1 "
0$
r5.9e1 %
#595000000
1!
1$
#600000000
0!
r6.0e1 "
0$
r6.0e1 %
#605000000
1!
1$
#610000000
0!
r6.1e1 "
0$
r6.1e1 %
#615000000
1!
1$
#620000000
0!
r6.2e1 "
0$
r6.2e1 %
#625000000
1!
1$
#630000000
0!
r6.3e1 "
0$
r6.3e1 %
#635000000
1!
1$
#640000000
0!
r6.4e1 "
r5.55e1 #
0$
r6.4e1 %
r5.55e1 &
#645000000
1!
1$
#650000000
0!
r6.5e1 "
0$
r6.5e1 %
#655000000
1!
1$
#660000000
0!
r6.6e1 "
0$
r6.6e1 %
#665000000
1!
1$
#670000000
0!
r6.7e1 "
0$
r6.7e1 %
#675000000
1!
1$
#680000000
0!
r6.8e1 "
0$
r6.8e1 %
#685000000
1!
1$
#690000000
0!
r6.9e1 "
0$
r6.9e1 %
#695000000
1!
1$
#700000000
0!
r7.0e1 "
0$
r7.0e1 %
#705000000
1!
1$
#710000000
0!
r7.1e1 "
0$
r7.1e1 %
#715000000
1!
1$
#720000000
0!
r7.2e1 "
0$
r7.2e1 %
#725000000
1!
1$
#730000000
0!
r7.3e1 "
0$
r7.3e1 %
#735000000
1!
1$
#740000000
0!
r7.4e1 "
0$
r7.4e1 %
#745000000
1!
1$
#750000000
0!
r7.5e1 "
0$
r7.5e1 %
#755000000
1!
1$
#760000000
0!
r7.6e1 "
0$
r7.6e1 %
#765000000
1!
1$
#770000000
0!
r7.7e1 "
0$
r7.7e1 %
#775000000
1!
1$
#780000000
0!
r7.8e1 "
0$
r7.8e1 %
#785000000
1!
1$
#790000000
0!
r7.9e1 "
0$
r7.9e1 %
#795000000
1!
1$
#800000000
0!
r8.0e1 "
r7.15e1 #
0$
r8.0e1 %
r7.15e1 &
#805000000
1!
1$
#810000000
0!
r8.1e1 "
0$
r8.1e1 %
#815000000
1!
1$
#820000000
0!
r8.2e1 "
0$
r8.2e1 %
#825000000
1!
1$
#830000000
0!
r8.3e1 "
0$
r8.3e1 %
#835000000
1!
1$
#840000000
0!
r8.4e1 "
0$
r8.4e1 %
#845000000
1!
1$
#850000000
0!
r8.5e1 "
0$
r8.5e1 %
#855000000
1!
1$
#860000000
0!
r8.6e1 "
0$
r8.6e1 %
#865000000
1!
1$
#870000000
0!
r8.7e1 "
0$
r8.7e1 %
#875000000
1!
1$
#880000000
0!
r8.8e1 "
0$
r8.8e1 %
#885000000
1!
1$
#890000000
0!
r8.9e1 "
0$
r8.9e1 %
#895000000
1!
1$
#900000000
0!
r9.0e1 "
0$
r9.0e1 %
#905000000
1!
1$
#910000000
0!
r9.1e1 "
0$
r9.1e1 %
#915000000
1!
1$
#920000000
0!
r9.2e1 "
0$
r9.2e1 %
#925000000
1!
1$
#930000000
0!
r9.3e1 "
0$
r9.3e1 %
#935000000
1!
1$
#940000000
0!
r9.4e1 "
0$
r9.4e1 %
#945000000
1!
1$
#950000000
0!
r9.5e1 "
0$
r9.5e1 %
#955000000
1!
1$
#960000000
0!
r9.6e1 "
r8.75e1 #
0$
r9.6e1 %
r8.75e1 &
#965000000
1!
1$
#970000000
0!
r9.7e1 "
0$
r9.7e1 %
#975000000
1!
1$
#980000000
0!
r9.8e1 "
0$
r9.8e1 %
#985000000
1!
1$
#990000000
0!
r9.9e1 "
0$
r9.9e1 %
#995000000
1!
1$
#1000000000
0!
r1.0e2 "
0$
r1.0e2 %
